gon/__init__.py
gon/base.py
gon/hints.py
gon/core/__init__.py
gon/core/angle.py
gon/core/compound.py
gon/core/contour.py
gon/core/empty.py
gon/core/geometry.py
gon/core/iterable.py
gon/core/mix.py
gon/core/multipoint.py
gon/core/multipolygon.py
gon/core/multisegment.py
gon/core/packing.py
gon/core/point.py
gon/core/polygon.py
gon/core/segment.py
gon/core/utils.py
gon/core/vector.py
gon/core/vertices.py
gon-6.0.0.dist-info/LICENSE
gon-6.0.0.dist-info/METADATA
gon-6.0.0.dist-info/WHEEL
gon-6.0.0.dist-info/top_level.txt
gon-6.0.0.dist-info/RECORD
