Metadata-Version: 2.1
Name: gon
Version: 6.0.0
Summary: Processing of planar geometries.
Home-page: https://github.com/lycantropos/gon/
Download-URL: https://github.com/lycantropos/gon/archive/master.zip
Author-email: Azat Ibrakov <azatibrakov@gmail.com>
License: MIT License
Classifier: License :: OSI Approved :: MIT License
Classifier: Programming Language :: Python :: 3.7
Classifier: Programming Language :: Python :: 3.8
Classifier: Programming Language :: Python :: 3.9
Classifier: Programming Language :: Python :: 3.10
Classifier: Programming Language :: Python :: 3.11
Classifier: Programming Language :: Python :: Implementation :: CPython
Classifier: Programming Language :: Python :: Implementation :: PyPy
Classifier: Programming Language :: Python :: Implementation :: CPython
Classifier: Programming Language :: Python :: Implementation :: PyPy
Requires-Python: >=3.7
License-File: LICENSE
Requires-Dist: bentley-ottmann (<9.0,>=8.0.0)
Requires-Dist: clipping (<7.0,>=6.0.0)
Requires-Dist: ground (<10.0,>=9.0.0)
Requires-Dist: locus (<11.0,>=10.0.0)
Requires-Dist: orient (<8.0,>=7.0.0)
Requires-Dist: reprit (<1.0,>=0.9.0)
Requires-Dist: sect (<8.0,>=7.0.0)
Requires-Dist: symba (<3.0,>=2.2.1)
Provides-Extra: tests
Requires-Dist: hypothesis (<7.0,>=6.75.3) ; extra == 'tests'
Requires-Dist: hypothesis-geometry (<9.0,>=8.0.0) ; extra == 'tests'
Requires-Dist: pytest (<8.0,>=7.3.1) ; extra == 'tests'
